[
  {"frame": 0, "time": 0.000, "state": 0},
  {"frame": 1, "time": 0.075, "state": 0},
  {"frame": 2, "time": 0.154, "state": 0},
  {"frame": 3, "time": 0.238, "state": 0},
  {"frame": 4, "time": 0.320, "state": 0},
  {"frame": 5, "time": 0.407, "state": 0},
  {"frame": 6, "time": 0.492, "state": 0},
  {"frame": 7, "time": 0.579, "state": 0},
  {"frame": 8, "time": 0.665, "state": 0},
  {"frame": 9, "time": 0.758, "state": 0},
  {"frame": 10, "time": 0.872, "state": 2},
  {"frame": 11, "time": 0.991, "state": 2},
  {"frame": 12, "time": 1.087, "state": 2},
  {"frame": 13, "time": 1.177, "state": 2},
  {"frame": 14, "time": 1.269, "state": 2},
  {"frame": 15, "time": 1.363, "state": 2},
  {"frame": 16, "time": 1.455, "state": 2},
  {"frame": 17, "time": 1.546, "state": 2},
  {"frame": 18, "time": 1.638, "state": 2},
  {"frame": 19, "time": 1.733, "state": 2},
  {"frame": 20, "time": 1.828, "state": 2},
  {"frame": 21, "time": 1.969, "state": 3},
  {"frame": 22, "time": 2.079, "state": 3},
  {"frame": 23, "time": 2.167, "state": 3},
  {"frame": 24, "time": 2.256, "state": 3},
  {"frame": 25, "time": 2.351, "state": 3},
  {"frame": 26, "time": 2.446, "state": 3},
  {"frame": 27, "time": 2.537, "state": 3},
  {"frame": 28, "time": 2.630, "state": 3},
  {"frame": 29, "time": 2.726, "state": 3},
  {"frame": 30, "time": 2.820, "state": 3},
  {"frame": 31, "time": 2.938, "state": 3},
  {"frame": 32, "time": 3.041, "state": 3},
  {"frame": 33, "time": 3.141, "state": 3},
  {"frame": 34, "time": 3.238, "state": 3},
  {"frame": 35, "time": 3.335, "state": 3},
  {"frame": 36, "time": 3.438, "state": 3},
  {"frame": 37, "time": 3.541, "state": 3},
  {"frame": 38, "time": 3.645, "state": 3},
  {"frame": 39, "time": 3.747, "state": 3},
  {"frame": 40, "time": 3.859, "state": 3},
  {"frame": 41, "time": 4.003, "state": 3},
  {"frame": 42, "time": 4.118, "state": 3},
  {"frame": 43, "time": 4.233, "state": 1},
  {"frame": 44, "time": 4.365, "state": 1},
  {"frame": 45, "time": 4.478, "state": 1},
  {"frame": 46, "time": 4.590, "state": 1},
  {"frame": 47, "time": 4.720, "state": 1},
  {"frame": 48, "time": 4.852, "state": 1},
  {"frame": 49, "time": 5.006, "state": 1},
  {"frame": 50, "time": 5.137, "state": 1},
  {"frame": 51, "time": 5.272, "state": 1},
  {"frame": 52, "time": 5.408, "state": 1},
  {"frame": 53, "time": 5.542, "state": 1},
  {"frame": 54, "time": 5.677, "state": 1},
  {"frame": 55, "time": 5.809, "state": 1},
  {"frame": 56, "time": 5.966, "state": 1},
  {"frame": 57, "time": 6.106, "state": 1},
  {"frame": 58, "time": 6.268, "state": 0},
  {"frame": 59, "time": 6.431, "state": 0},
  {"frame": 60, "time": 6.571, "state": 0},
  {"frame": 61, "time": 6.710, "state": 0},
  {"frame": 62, "time": 6.857, "state": 0},
  {"frame": 63, "time": 7.028, "state": 0},
  {"frame": 64, "time": 7.177, "state": 0},
  {"frame": 65, "time": 7.322, "state": 0},
  {"frame": 66, "time": 7.469, "state": 0},
  {"frame": 67, "time": 7.619, "state": 0},
  {"frame": 68, "time": 7.770, "state": 0},
  {"frame": 69, "time": 7.936, "state": 0},
  {"frame": 70, "time": 8.088, "state": 0},
  {"frame": 71, "time": 8.259, "state": 1},
  {"frame": 72, "time": 8.416, "state": 1},
  {"frame": 73, "time": 8.567, "state": 1},
  {"frame": 74, "time": 8.746, "state": 3},
  {"frame": 75, "time": 8.941, "state": 3},
  {"frame": 76, "time": 9.091, "state": 3},
  {"frame": 77, "time": 9.238, "state": 3},
  {"frame": 78, "time": 9.389, "state": 3},
  {"frame": 79, "time": 9.551, "state": 3},
  {"frame": 80, "time": 9.705, "state": 3},
  {"frame": 81, "time": 9.865, "state": 3},
  {"frame": 82, "time": 10.024, "state": 3},
  {"frame": 83, "time": 10.168, "state": 3},
  {"frame": 84, "time": 10.348, "state": 3},
  {"frame": 85, "time": 10.509, "state": 0},
  {"frame": 86, "time": 10.671, "state": 0},
  {"frame": 87, "time": 10.819, "state": 0},
  {"frame": 88, "time": 10.977, "state": 0},
  {"frame": 89, "time": 11.180, "state": 1},
  {"frame": 90, "time": 11.344, "state": 1},
  {"frame": 91, "time": 11.495, "state": 1},
  {"frame": 92, "time": 11.645, "state": 1},
  {"frame": 93, "time": 11.801, "state": 1},
  {"frame": 94, "time": 11.963, "state": 1},
  {"frame": 95, "time": 12.128, "state": 1},
  {"frame": 96, "time": 12.286, "state": 1},
  {"frame": 97, "time": 12.460, "state": 1},
  {"frame": 98, "time": 12.637, "state": 1},
  {"frame": 99, "time": 12.812, "state": 1},
  {"frame": 100, "time": 13.016, "state": 1},
  {"frame": 101, "time": 13.196, "state": 1},
  {"frame": 102, "time": 13.373, "state": 1},
  {"frame": 103, "time": 13.557, "state": 1},
  {"frame": 104, "time": 13.768, "state": 0},
  {"frame": 105, "time": 13.968, "state": 0},
  {"frame": 106, "time": 14.156, "state": 0},
  {"frame": 107, "time": 14.371, "state": 2},
  {"frame": 108, "time": 14.568, "state": 2},
  {"frame": 109, "time": 14.759, "state": 2},
  {"frame": 110, "time": 14.987, "state": 0},
  {"frame": 111, "time": 15.188, "state": 0},
  {"frame": 112, "time": 15.382, "state": 0},
  {"frame": 113, "time": 15.584, "state": 0},
  {"frame": 114, "time": 15.821, "state": 4},
  {"frame": 115, "time": 16.018, "state": 4},
  {"frame": 116, "time": 16.216, "state": 4},
  {"frame": 117, "time": 16.413, "state": 4},
  {"frame": 118, "time": 16.608, "state": 4},
  {"frame": 119, "time": 16.812, "state": 0},
  {"frame": 120, "time": 17.054, "state": 0},
  {"frame": 121, "time": 17.251, "state": 0},
  {"frame": 122, "time": 17.468, "state": 2},
  {"frame": 123, "time": 17.670, "state": 2},
  {"frame": 124, "time": 17.898, "state": 4},
  {"frame": 125, "time": 18.103, "state": 4},
  {"frame": 126, "time": 18.301, "state": 4},
  {"frame": 127, "time": 18.533, "state": 4},
  {"frame": 128, "time": 18.737, "state": 4},
  {"frame": 129, "time": 18.969, "state": 4},
  {"frame": 130, "time": 19.183, "state": 4},
  {"frame": 131, "time": 19.396, "state": 4},
  {"frame": 132, "time": 19.618, "state": 4},
  {"frame": 133, "time": 19.848, "state": 4},
  {"frame": 134, "time": 20.078, "state": 4},
  {"frame": 135, "time": 20.294, "state": 4},
  {"frame": 136, "time": 20.508, "state": 4},
  {"frame": 137, "time": 20.742, "state": 4},
  {"frame": 138, "time": 20.991, "state": 4},
  {"frame": 139, "time": 21.208, "state": 4},
  {"frame": 140, "time": 21.428, "state": 4},
  {"frame": 141, "time": 21.646, "state": 4},
  {"frame": 142, "time": 21.875, "state": 4},
  {"frame": 143, "time": 22.105, "state": 4},
  {"frame": 144, "time": 22.361, "state": 2},
  {"frame": 145, "time": 22.592, "state": 2},
  {"frame": 146, "time": 22.831, "state": 2},
  {"frame": 147, "time": 23.099, "state": 2},
  {"frame": 148, "time": 23.350, "state": 2},
  {"frame": 149, "time": 23.597, "state": 2},
  {"frame": 150, "time": 23.848, "state": 2},
  {"frame": 151, "time": 24.105, "state": 2},
  {"frame": 152, "time": 24.358, "state": 2},
  {"frame": 153, "time": 24.606, "state": 2},
  {"frame": 154, "time": 24.861, "state": 2},
  {"frame": 155, "time": 25.126, "state": 2},
  {"frame": 156, "time": 25.369, "state": 2},
  {"frame": 157, "time": 25.609, "state": 2},
  {"frame": 158, "time": 25.858, "state": 2},
  {"frame": 159, "time": 26.119, "state": 2},
  {"frame": 160, "time": 26.375, "state": 2},
  {"frame": 161, "time": 26.634, "state": 2},
  {"frame": 162, "time": 26.912, "state": 2},
  {"frame": 163, "time": 27.170, "state": 2},
  {"frame": 164, "time": 27.429, "state": 2},
  {"frame": 165, "time": 27.693, "state": 2},
  {"frame": 166, "time": 27.994, "state": 4},
  {"frame": 167, "time": 28.263, "state": 4},
  {"frame": 168, "time": 28.525, "state": 4},
  {"frame": 169, "time": 28.818, "state": 4},
  {"frame": 170, "time": 29.117, "state": 4},
  {"frame": 171, "time": 29.381, "state": 4},
  {"frame": 172, "time": 29.646, "state": 4},
  {"frame": 173, "time": 29.938, "state": 4},
  {"frame": 174, "time": 30.233, "state": 1},
  {"frame": 175, "time": 30.525, "state": 1},
  {"frame": 176, "time": 30.810, "state": 1},
  {"frame": 177, "time": 31.137, "state": 1},
  {"frame": 178, "time": 31.442, "state": 1},
  {"frame": 179, "time": 31.737, "state": 1},
  {"frame": 180, "time": 32.055, "state": 1},
  {"frame": 181, "time": 32.360, "state": 1},
  {"frame": 182, "time": 32.667, "state": 1},
  {"frame": 183, "time": 32.988, "state": 1},
  {"frame": 184, "time": 33.290, "state": 1},
  {"frame": 185, "time": 33.596, "state": 1},
  {"frame": 186, "time": 33.911, "state": 1},
  {"frame": 187, "time": 34.210, "state": 1},
  {"frame": 188, "time": 34.508, "state": 1},
  {"frame": 189, "time": 34.838, "state": 1},
  {"frame": 190, "time": 35.132, "state": 1},
  {"frame": 191, "time": 35.450, "state": 1},
  {"frame": 192, "time": 35.757, "state": 1},
  {"frame": 193, "time": 36.058, "state": 1},
  {"frame": 194, "time": 36.368, "state": 1},
  {"frame": 195, "time": 36.679, "state": 1},
  {"frame": 196, "time": 36.988, "state": 1},
  {"frame": 197, "time": 37.299, "state": 1},
  {"frame": 198, "time": 37.613, "state": 1},
  {"frame": 199, "time": 37.923, "state": 1},
  {"frame": 200, "time": 38.255, "state": 0},
  {"frame": 201, "time": 38.560, "state": 0},
  {"frame": 202, "time": 38.892, "state": 0},
  {"frame": 203, "time": 39.210, "state": 0},
  {"frame": 204, "time": 39.509, "state": 0},
  {"frame": 205, "time": 39.823, "state": 0},
  {"frame": 206, "time": 40.124, "state": 0},
  {"frame": 207, "time": 40.429, "state": 0},
  {"frame": 208, "time": 40.734, "state": 0},
  {"frame": 209, "time": 41.052, "state": 0},
  {"frame": 210, "time": 41.371, "state": 0},
  {"frame": 211, "time": 41.685, "state": 0},
  {"frame": 212, "time": 42.038, "state": 0},
  {"frame": 213, "time": 42.379, "state": 2},
  {"frame": 214, "time": 42.729, "state": 2},
  {"frame": 215, "time": 43.086, "state": 2},
  {"frame": 216, "time": 43.448, "state": 0},
  {"frame": 217, "time": 43.785, "state": 0},
  {"frame": 218, "time": 44.141, "state": 0},
  {"frame": 219, "time": 44.486, "state": 0},
  {"frame": 220, "time": 44.839, "state": 0},
  {"frame": 221, "time": 45.184, "state": 0},
  {"frame": 222, "time": 45.535, "state": 0},
  {"frame": 223, "time": 45.892, "state": 0}
]
